softwareappenergycalc.py
softwareappenergycalc-0.0.5.dist-info/METADATA
softwareappenergycalc-0.0.5.dist-info/WHEEL
softwareappenergycalc-0.0.5.dist-info/top_level.txt
softwareappenergycalc-0.0.5.dist-info/RECORD
